multibind/__init__.py
multibind/chem.py
multibind/multibind.py
multibind/nonequilibrium.py
multibind-0.2.0.dist-info/LICENSE
multibind-0.2.0.dist-info/WHEEL
multibind-0.2.0.dist-info/METADATA
multibind-0.2.0.dist-info/RECORD
